{
    "1": {
        "project_name": "dispenser install",
        "cust_number": 11990,
        "begin_date": "2021-01-30",
        "end_date": "2021-05-30",
        "project_email": "customer@company.com",
        "complete_pct": "10"
    },
    "2": {
        "project_name": "equipment sale",
        "cust_number": 11990,
        "begin_date": "2021-02-28",
        "end_date": "2021-03-31",
        "project_email": "customer23@abc.com",
        "complete_pct": "0"
    },
    "3": {
        "project_name": "paper conversion",
        "cust_number": 16330,
        "begin_date": "2021-05-08",
        "end_date": "2021-08-11",
        "project_email": "customer3@123.com",
        "complete_pct": "20"
    }

}
